imgbbpy/__init__.py
imgbbpy/imgbb.py
imgbbpy/imgerrors.py
imgbbpy/imggallery.py
imgbbpy-0.1.3.dist-info/LICENSE
imgbbpy-0.1.3.dist-info/METADATA
imgbbpy-0.1.3.dist-info/WHEEL
imgbbpy-0.1.3.dist-info/top_level.txt
imgbbpy-0.1.3.dist-info/RECORD
