Metadata-Version: 2.1
Name: imgbbpy
Version: 0.1.3
Summary: An Asynchronous and Synchronous API Wrapper for the Imgbb API.
Home-page: https://github.com/scrazzz/imgbbpy/
Author: scrazzz
License: MIT
Project-URL: Documentation, https://github.com/scrazzz/imgbbpy/blob/main/documentation.md
Project-URL: Issue tracker, https://github.com/scrazzz/imgbbpy/issues
Platform: UNKNOWN
Requires-Python: >=3.7.0
